CHANGELOG.md
README.md
kleinmann/__init__.py
kleinmann/backends/__init__.py
kleinmann/backends/asyncpg/__init__.py
kleinmann/backends/asyncpg/client.py
kleinmann/backends/asyncpg/executor.py
kleinmann/backends/asyncpg/schema_generator.py
kleinmann/backends/base/__init__.py
kleinmann/backends/base/client.py
kleinmann/backends/base/config_generator.py
kleinmann/backends/base/executor.py
kleinmann/backends/base/schema_generator.py
kleinmann/backends/base_postgres/__init__.py
kleinmann/backends/base_postgres/client.py
kleinmann/backends/base_postgres/executor.py
kleinmann/backends/base_postgres/schema_generator.py
kleinmann/backends/sqlite/__init__.py
kleinmann/backends/sqlite/client.py
kleinmann/backends/sqlite/executor.py
kleinmann/backends/sqlite/schema_generator.py
kleinmann/connection.py
kleinmann/contrib/__init__.py
kleinmann/contrib/aiohttp/__init__.py
kleinmann/contrib/blacksheep/__init__.py
kleinmann/contrib/fastapi/__init__.py
kleinmann/contrib/postgres/__init__.py
kleinmann/contrib/postgres/fields.py
kleinmann/contrib/postgres/functions.py
kleinmann/contrib/postgres/indexes.py
kleinmann/contrib/postgres/json_functions.py
kleinmann/contrib/postgres/search.py
kleinmann/contrib/pydantic/__init__.py
kleinmann/contrib/pydantic/base.py
kleinmann/contrib/pydantic/creator.py
kleinmann/contrib/pydantic/utils.py
kleinmann/contrib/pylint/__init__.py
kleinmann/contrib/quart/__init__.py
kleinmann/contrib/sanic/__init__.py
kleinmann/contrib/sqlite/__init__.py
kleinmann/contrib/sqlite/functions.py
kleinmann/contrib/starlette/__init__.py
kleinmann/contrib/test/__init__.py
kleinmann/contrib/test/condition.py
kleinmann/converters.py
kleinmann/exceptions.py
kleinmann/expressions.py
kleinmann/fields/__init__.py
kleinmann/fields/base.py
kleinmann/fields/data.py
kleinmann/fields/relational.py
kleinmann/filters.py
kleinmann/functions.py
kleinmann/indexes.py
kleinmann/log.py
kleinmann/manager.py
kleinmann/models.py
kleinmann/py.typed
kleinmann/query_utils.py
kleinmann/queryset.py
kleinmann_orm-0.0.2.dist-info/LICENSE.txt
kleinmann_orm-0.0.2.dist-info/METADATA
kleinmann_orm-0.0.2.dist-info/WHEEL
kleinmann_orm-0.0.2.dist-info/RECORD
