Metadata-Version: 2.1
Name: kleinmann-orm
Version: 0.0.2
Summary: A tiny tortoise ORM
Home-page: https://github.com/kleinmann-orm/kleinmann-orm
License: Apache-2.0
Keywords: sql,postgres,sqlite,aiosqlite,asyncpg,relational,database,rdbms,orm,object mapper,async,asyncio,aio
Author: Lev Gorodetskii
Author-email: github@drsr.io
Maintainer: Lev Gorodetskii
Maintainer-email: github@drsr.io
Requires-Python: >=3.8,<4.0
Classifier: Development Status :: 3 - Alpha
Classifier: Framework :: AsyncIO
Classifier: Intended Audience :: Developers
Classifier: License :: OSI Approved :: Apache Software License
Classifier: Operating System :: MacOS :: MacOS X
Classifier: Operating System :: POSIX
Classifier: Programming Language :: PL/SQL
Classifier: Programming Language :: Python :: 3
Classifier: Programming Language :: Python :: 3.8
Classifier: Programming Language :: Python :: 3.9
Classifier: Programming Language :: Python :: 3.10
Classifier: Programming Language :: Python :: 3.11
Classifier: Programming Language :: Python :: 3.12
Classifier: Programming Language :: Python :: Implementation :: CPython
Classifier: Programming Language :: Python :: Implementation :: PyPy
Classifier: Topic :: Database
Classifier: Topic :: Software Development :: Libraries :: Python Modules
Provides-Extra: accel
Requires-Dist: aiosqlite (>=0.20.0)
Requires-Dist: asyncpg
Requires-Dist: ciso8601 ; (sys_platform != "win32" and implementation_name == "cpython") and (extra == "accel")
Requires-Dist: iso8601 (>=1.0.2,<2.0.0)
Requires-Dist: orjson ; extra == "accel"
Requires-Dist: pydantic (>=2.0,<3.0,!=2.7.0,<2.9.0)
Requires-Dist: pytz
Requires-Dist: uvloop ; (sys_platform != "win32" and implementation_name == "cpython") and (extra == "accel")
Project-URL: Documentation, https://github.com/kleinmann-orm/kleinmann-orm
Project-URL: Repository, https://github.com/kleinmann-orm/kleinmann-orm.git
